setup.cfg
setup.py
kuliza_ip2location/__init__.py
kuliza_ip2location/ip2location.py
kuliza_ip2location.egg-info/PKG-INFO
kuliza_ip2location.egg-info/SOURCES.txt
kuliza_ip2location.egg-info/dependency_links.txt
kuliza_ip2location.egg-info/requires.txt
kuliza_ip2location.egg-info/top_level.txt