Metadata-Version: 1.0
Name: kuliza-ip2location
Version: 0.1
Summary: Wrapper for https://ipinfo.io
Home-page: https://www.example.com/
Author: Sachin Prabhu
Author-email: sachin.prabhu@kuliza.com
License: UNKNOWN
Platform: UNKNOWN
